nrask/__init__.py
nrask/base/__init__.py
nrask/debug/__init__.py
nrask/http/__init__.py
nrask/io/__init__.py
nrask/io/utcode/__init__.py
nrask/ioengine/__init__.py
nrask/main/__init__.py
nrask/options/__init__.py
nrask/parser/__init__.py
nrask/parser/bencode/__init__.py
nrask/parser/date/__init__.py
nrask/parser/json/__init__.py
nrask/parser/utcode/__init__.py
nrask/raven/__init__.py
nrask/rmq/__init__.py
nrask/rmq/ack.py
nrask/rmq/announce.py
nrask/rmq/channel.py
nrask/rmq/connection.py
nrask/rmq/retry.py
nrask-0.0.116.dist-info/METADATA
nrask-0.0.116.dist-info/RECORD
nrask-0.0.116.dist-info/WHEEL
nrask-0.0.116.dist-info/top_level.txt
